sequana_pipelines/bioconvert/__init__.py
sequana_pipelines/bioconvert/bioconvert.rules
sequana_pipelines/bioconvert/config.yaml
sequana_pipelines/bioconvert/dag.png
sequana_pipelines/bioconvert/dag.svg
sequana_pipelines/bioconvert/data/__init__.py
sequana_pipelines/bioconvert/data/data_R1_001.fasta.gz
sequana_pipelines/bioconvert/data/data_R1_001.fastq.gz
sequana_pipelines/bioconvert/data/data_R2_001.fasta.gz
sequana_pipelines/bioconvert/data/data_R2_001.fastq.gz
sequana_pipelines/bioconvert/main.py
sequana_pipelines/bioconvert/schema.yaml
sequana_pipelines/bioconvert/tools.txt
sequana_bioconvert-1.1.0.dist-info/LICENSE
sequana_bioconvert-1.1.0.dist-info/METADATA
sequana_bioconvert-1.1.0.dist-info/WHEEL
sequana_bioconvert-1.1.0.dist-info/entry_points.txt
sequana_bioconvert-1.1.0.dist-info/RECORD
